unacalc/__init__.py
unacalc/main.py
unacalc-1.0.3.dist-info/LICENSE
unacalc-1.0.3.dist-info/METADATA
unacalc-1.0.3.dist-info/WHEEL
unacalc-1.0.3.dist-info/entry_points.txt
unacalc-1.0.3.dist-info/top_level.txt
unacalc-1.0.3.dist-info/RECORD
