Metadata-Version: 2.1
Name: unacalc
Version: 1.0.3
Summary: Unacalc: A Unit-Aware Calculator
Home-page: https://github.com/tovam/unacalc
Author: tovam
Author-email: tovam@proton.me
Classifier: Programming Language :: Python :: 3
Classifier: License :: OSI Approved :: GNU General Public License v3 (GPLv3)
Classifier: Operating System :: OS Independent
Requires-Python: >=3.6
License-File: LICENSE
Requires-Dist: PyQt5
Requires-Dist: pint
Requires-Dist: numpy
Requires-Dist: pyparsing
